llm_batch_processor/__init__.py
llm_batch_processor/api_client.py
llm_batch_processor/config.py
llm_batch_processor/get_prompt.py
llm_batch_processor/processor.py
scripts/__init__.py
scripts/main.py
llm_batch_processor-0.1.4.dist-info/LICENSE
llm_batch_processor-0.1.4.dist-info/METADATA
llm_batch_processor-0.1.4.dist-info/WHEEL
llm_batch_processor-0.1.4.dist-info/entry_points.txt
llm_batch_processor-0.1.4.dist-info/top_level.txt
llm_batch_processor-0.1.4.dist-info/RECORD
