Metadata-Version: 2.2
Name: llm_batch_processor
Version: 0.1.4
Summary: A package to process CSV text data in batches using OpenAI API
Home-page: https://github.com/karthikRavichandran/llm_batch_processor
Author: Karthik Ravichandran
Author-email: tkgravikarthik@gmail.com
License: MIT
Classifier: Programming Language :: Python :: 3
Classifier: License :: OSI Approved :: MIT License
Classifier: Operating System :: OS Independent
Requires-Python: >=3.7
License-File: LICENSE
Requires-Dist: openai
Requires-Dist: pandas
Requires-Dist: python-dotenv
Requires-Dist: tqdm
Dynamic: author
Dynamic: author-email
Dynamic: classifier
Dynamic: description
Dynamic: description-content-type
Dynamic: home-page
Dynamic: requires-dist
Dynamic: requires-python
Dynamic: summary
